{"cameraMode":{"drawMode":0,"name":"Shaded","section":"Shading Mode"},"sceneLighting":true,"audioPlay":false,"sceneViewState":{"m_AlwaysRefresh":false,"showFog":true,"showSkybox":true,"showFlares":true,"showImageEffects":true,"showParticleSystems":true,"showVisualEffectGraphs":true,"m_FxEnabled":true},"in2DMode":false,"pivot":{"x":345.3844909667969,"y":333.6322326660156,"z":-262.1107482910156},"rotation":{"x":0.07486402988433838,"y":0.12228889763355255,"z":-0.007915089838206768,"w":0.9912092089653015},"size":35.61189651489258,"orthographic":false}